gherkin2robotframework/__init__.py
gherkin2robotframework/__main__.py
gherkin2robotframework/dumpgherkin.py
gherkin2robotframework/translation.py
gherkin2robotframework-0.4.2.dist-info/LICENSE
gherkin2robotframework-0.4.2.dist-info/METADATA
gherkin2robotframework-0.4.2.dist-info/WHEEL
gherkin2robotframework-0.4.2.dist-info/entry_points.txt
gherkin2robotframework-0.4.2.dist-info/top_level.txt
gherkin2robotframework-0.4.2.dist-info/RECORD
