Metadata-Version: 2.1
Name: gherkin2robotframework
Version: 0.4.2
Summary: Translate Gherkin feature files into RobotFramework tests
Author-email: Maurice Koster <maurice@mauricekoster.com>
License: The MIT License (MIT)
Project-URL: Repository, https://github.com/mauricekoster/gherkin2robotframework.git
Keywords: gherkin,robotframework
Classifier: Programming Language :: Python :: 3
Classifier: License :: OSI Approved :: MIT License
Classifier: Operating System :: OS Independent
Requires-Python: >=3.9
License-File: LICENSE
Requires-Dist: gherkin-official ==30.0.4
Requires-Dist: pyyaml ==6.0.2
